inception_pagination/__init__.py
inception_pagination/pagination.py
inception_pagination-0.1.0.dist-info/LICENSE
inception_pagination-0.1.0.dist-info/METADATA
inception_pagination-0.1.0.dist-info/WHEEL
inception_pagination-0.1.0.dist-info/top_level.txt
inception_pagination-0.1.0.dist-info/RECORD
